[
  {
    "id": 1,
    "userId": 1,
    "createdAt": "2025-07-10 09:00:00",
    "updatedAt": "2025-07-10 09:00:00"
  },
  {
    "id": 2,
    "userId": 2,
    "createdAt": "2025-07-10 10:15:00",
    "updatedAt": "2025-07-10 10:15:00"
  },
  {
    "id": 3,
    "userId": 3,
    "createdAt": "2025-07-10 11:30:00",
    "updatedAt": "2025-07-10 11:30:00"
  },
  {
    "id": 4,
    "userId": 4,
    "createdAt": "2025-07-10 12:45:00",
    "updatedAt": "2025-07-10 12:45:00"
  },
  {
    "id": 5,
    "userId": 5,
    "createdAt": "2025-07-10 14:00:00",
    "updatedAt": "2025-07-10 14:00:00"
  },
  {
    "id": 6,
    "userId": 6,
    "createdAt": "2025-07-10 15:30:00",
    "updatedAt": "2025-07-10 15:30:00"
  },
  {
    "id": 7,
    "userId": 7,
    "createdAt": "2025-07-10 16:45:00",
    "updatedAt": "2025-07-10 16:45:00"
  },
  {
    "id": 8,
    "userId": 8,
    "createdAt": "2025-07-10 17:50:00",
    "updatedAt": "2025-07-10 17:50:00"
  },
  {
    "id": 9,
    "userId": 9,
    "createdAt": "2025-07-10 18:30:00",
    "updatedAt": "2025-07-10 18:30:00"
  },
  {
    "id": 10,
    "userId": 10,
    "createdAt": "2025-07-10 19:10:00",
    "updatedAt": "2025-07-10 19:10:00"
  }
]
